LICENSE
README.md
pyfa_converter_v2/__init__.py
pyfa_converter_v2/depends.py
pyfa_converter_v2/main.py
pyfa_converter_v2/py.typed
pyfa_converter_v2-2.0.0rc1.dist-info/LICENSE
pyfa_converter_v2-2.0.0rc1.dist-info/METADATA
pyfa_converter_v2-2.0.0rc1.dist-info/WHEEL
pyfa_converter_v2-2.0.0rc1.dist-info/RECORD
