Metadata-Version: 2.1
Name: pyfa-converter-v2
Version: 2.0.0rc1
Summary: Pydantic to FastAPI model converter.
Home-page: https://github.com/AezaGroup/pyfa-converter-v2
License: LGPL-3.0-only
Author: Egor Ternovoy
Author-email: cofob@riseup.net
Requires-Python: >=3.8.1,<4.0
Classifier: License :: OSI Approved :: GNU Lesser General Public License v3 (LGPLv3)
Classifier: Programming Language :: Python :: 3
Classifier: Programming Language :: Python :: 3.9
Classifier: Programming Language :: Python :: 3.10
Classifier: Programming Language :: Python :: 3.11
Classifier: Programming Language :: Python :: 3.12
Requires-Dist: fastapi (>=0.100)
Requires-Dist: pydantic (>=2)
Project-URL: Repository, https://github.com/AezaGroup/pyfa-converter-v2
